.gitignore
.travis.yml
LICENSE
Makefile
README.md
SUPPORTED_PROFILES.md
generate_supported_profiles.py
requirements.txt
run_tests_with_timing.sh
setup.py
asyncenocean/__init__.py
asyncenocean/consolelogger.py
asyncenocean/decorators.py
asyncenocean/utils.py
asyncenocean.egg-info/PKG-INFO
asyncenocean.egg-info/SOURCES.txt
asyncenocean.egg-info/dependency_links.txt
asyncenocean.egg-info/requires.txt
asyncenocean.egg-info/top_level.txt
asyncenocean/communicators/__init__.py
asyncenocean/communicators/communicator.py
asyncenocean/communicators/serialcommunicator.py
asyncenocean/communicators/tcpcommunicator.py
asyncenocean/communicators/utils.py
asyncenocean/communicators/tests/test_communicator.py
asyncenocean/protocol/EEP.xml
asyncenocean/protocol/__init__.py
asyncenocean/protocol/constants.py
asyncenocean/protocol/crc8.py
asyncenocean/protocol/eep.py
asyncenocean/protocol/packet.py
asyncenocean/protocol/tests/test_eep.py
asyncenocean/protocol/tests/test_packet.py
asyncenocean/protocol/tests/test_packet_creation.py
asyncenocean/protocol/tests/test_teachin.py
asyncenocean/protocol/tests/test_temperature_sensors.py
asyncenocean/tests/test_utils.py
examples/co_rd_version_example.py
examples/enocean_example.py
examples/example_D2-05-00.py
examples/example_DO21-11B-E.py
examples/serial_to_tcp.py
examples/tcp_server.py